{"absolute_url":"https://lilium.com/jobs/5154573?gh_jid=5154573","data_compliance":[{"type":"gdpr","requires_consent":true,"requires_processing_consent":true,"requires_retention_consent":true,"retention_period":730}],"internal_job_id":2580078,"location":{"name":"Munich"},"metadata":[{"id":167984,"name":"Position Type","value":"Full time Permanent","value_type":"single_select"},{"id":107112,"name":"Division","value":"Engineering","value_type":"single_select"}],"id":5154573,"updated_at":"2023-08-21T06:08:44-04:00","requisition_id":"2590","title":"Analysis Engineer – Propulsion","pay_input_ranges":[],"content":"A career at Lilium is for those who want to do something extraordinary. We take pride in pushing the boundaries of engineering, technology and customer experience.  \nAs part of a team, you will tackle challenges and deliver something that has never been done before. By joining Lilium you will have the opportunity to work with a world-class entrepreneurial team of more than  800 people who are  as passionate about changing the world as you are.  \nYou will always act with safety and integrity in mind and embody our core behaviors of efficient and positive collaboration, ownership of time, continuous improvements and, ultimately delivering results.\nWe thrive on diversity and creating an inclusive culture, with more than 50 nationalities currently working hard to bring our vision of a sustainable world to life. The Role:\nWe are looking for an outstanding Analysis engineer with a strong background in structural stress analysis for engines to join our innovative team and help us shape the future of urban e-mobility.\nIn this position, you will have the exciting opportunity to work within the rapidly growing Structural Analysis Team as part of the Design and Aerostructures Function. You will report to a Structural Analysis Team Lead and be part of the multi-disciplinary Integrated Project Team for Propulsion.\nLilium welcomes people from all over the world. We are a multinational company and happy to support our new top talents with relocation. We have helped our new hires to meet their Visa criteria and successfully settle in Munich.\nYour Day to Day:\n Sizing and stress analysis of rotating and static propulsion unit structures by means of hand calculations, numerical simulations (FEM) and optimization techniques\n\nCreate, manage and validate detailed FE models of complete propulsion structures and systems, with responsibility for the full workflow of numerical modelling, solving and post-processing\nYou will have a particular focus on topics such as:\n\nLinear and non-linear static analysis\nFatigue analysis (LCF, HCF)\nFracture mechanics analysis\nVibration analysis such as Modal, Harmonic or forced response, Random vibration, Rotor dynamics)\n\n\nModel correlation with static and dynamic test data for certification purposes\nCreation of clear and concise technical reports and documentation\nReviewing and checking of internal and supplier analysis data\nWork closely with your Team Lead, Engineering Suppliers and Engineers from Mechanical Design, Manufacturing and Testing throughout the entire product development process to develop propulsion unit structures and attachments with exceptional performance\n\n Your profile: \n\nEngineering degree in Aerospace Engineering, Mechanical Engineering or related field is required\n5+ years of experience in Structural analysis, with application to engines and/or turbomachinery\nExcellent knowledge of stress analysis methods, including vibration analysis.\nConfidence in the application of optimization techniques\nIn-depth understanding of the loading scenarios and mechanical behaviour of aircraft structures, particularly complex multipart assemblies\nExtensive working experience with the commercial implicit FE code OptiStruct, and corresponding pre- and post-processing tools (HyperMesh and HyperView) is a must\nMotivated, initiative and driven problem-solving attitude are critical as well as a high level of self-reliance and an autonomous target-oriented work style\nFluent English language skills are essential, fluent German or any other language would be beneficial\n\n#LI-K1Want to know more? Then view our 'Why join Lilium' page!\nLife at Lilium:\nThe wellbeing of our employees is a high priority. In our HQ we have many initiatives such as free healthy food and drinks, free in-house gym and health days. In remote offices we offer online opportunities to stay connected and develop yourself as well including our culture club, learning terminal, Employee Assistance Program and many more.\n Lilium is an equal opportunity employer and welcomes applications from all qualified individuals regardless of ethnicity, sex, disability, religion/belief, sexual orientation or age.  \n \n ","departments":[{"id":28112,"name":"Design & Aerostructures","child_ids":[],"parent_id":69931}],"offices":[{"id":74957,"name":"Lilium eAircraft GmbH","location":"Weßling, Bavaria, Germany","child_ids":[],"parent_id":null}],"compliance":null,"demographic_questions":null,"questions":[{"description":null,"label":"First Name","required":true,"fields":[{"name":"first_name","type":"input_text","values":[]}]},{"description":null,"label":"Last Name","required":true,"fields":[{"name":"last_name","type":"input_text","values":[]}]},{"description":null,"label":"Email","required":true,"fields":[{"name":"email","type":"input_text","values":[]}]},{"description":null,"label":"Phone","required":false,"fields":[{"name":"phone","type":"input_text","values":[]}]},{"description":null,"label":"Resume/CV","required":true,"fields":[{"name":"resume","type":"input_file","values":[]},{"name":"resume_text","type":"textarea","values":[]}]},{"description":null,"label":"Cover Letter","required":false,"fields":[{"name":"cover_letter","type":"input_file","values":[]},{"name":"cover_letter_text","type":"textarea","values":[]}]},{"description":null,"label":"Additional document / Certificates / Portfolio","required":false,"fields":[{"name":"question_41067266","type":"input_file","values":[]}]},{"description":"<p><a href=\"https://eur02.safelinks.protection.outlook.com/?url=https%3A%2F%2Flilium.com%2Fprivacy-policy&amp;data=05%7C01%7Cjudith.wubben%40lilium.com%7C8aa5bd87e1064afa1d8308da8f421a70%7Cba06cbf3c66148968dbccd190052c299%7C0%7C0%7C637979811318725912%7CUnknown%7CTWFpbGZsb3d8eyJWIjoiMC4wLjAwMDAiLCJQIjoiV2luMzIiLCJBTiI6Ik1haWwiLCJXVCI6Mn0%3D%7C3000%7C%7C%7C&amp;sdata=lqnwTVccxPF9ch3qiSi%2FmteOfmRavD9c3NEhkRsziWA%3D&amp;reserved=0\" target=\"_blank\" rel=\"noopener\">Lilium Website Privacy Notice</a></p>\n<p><a href=\"https://eur02.safelinks.protection.outlook.com/?url=https%3A%2F%2Flilium.com%2Fprivacy-in-recruiting&amp;data=05%7C01%7Cjudith.wubben%40lilium.com%7C8aa5bd87e1064afa1d8308da8f421a70%7Cba06cbf3c66148968dbccd190052c299%7C0%7C0%7C637979811318882120%7CUnknown%7CTWFpbGZsb3d8eyJWIjoiMC4wLjAwMDAiLCJQIjoiV2luMzIiLCJBTiI6Ik1haWwiLCJXVCI6Mn0%3D%7C3000%7C%7C%7C&amp;sdata=qBR1n4vHKev0x29OPTXjHETt%2BsUyA7AvmUu6ek8mOnI%3D&amp;reserved=0\" target=\"_blank\" rel=\"noopener\">Lilium Recruitment Privacy Notice</a></p>\n<p>**<strong><em> For clarity, to comply with our legal obligations, Lilium will collect, store, and process your data for 6 months for the purpose of considering you for employment.&nbsp; Additionally, should you provide consent directly below, Lilium will also collect, store, and process your data for up to 730 days thereafter for the purpose of considering you for other opportunities on the Lilium Career Portal.</em></strong></p>","label":"Data Protection Information","required":true,"fields":[{"name":"question_41067267","type":"multi_value_single_select","values":[{"label":"I confirm that I have read and understood the Lilium Website Privacy Notice and the Lilium Recruitment Privacy Notice, regarding the collection, processing and storage of my personal data for the recruitment process.","value":138174166}]}]},{"description":null,"label":"LinkedIn Profile / Website","required":false,"fields":[{"name":"question_41067268","type":"input_text","values":[]}]},{"description":null,"label":"IMPORTANT: I confirm I have submitted my CV in English, and understand that my application will not be reviewed if it is in another language","required":true,"fields":[{"name":"question_41067269","type":"multi_value_single_select","values":[{"label":"I can confirm","value":138174167}]}]}],"location_questions":[]}